ku/__init__.py
ku/ku.py
ku/kun.py
ku/util.py
ku_proxy-0.2.1.dist-info/LICENSE
ku_proxy-0.2.1.dist-info/METADATA
ku_proxy-0.2.1.dist-info/WHEEL
ku_proxy-0.2.1.dist-info/entry_points.txt
ku_proxy-0.2.1.dist-info/top_level.txt
ku_proxy-0.2.1.dist-info/RECORD
