Metadata-Version: 2.1
Name: ku-proxy
Version: 0.2.1
Summary: ku is fast, async, modern, little tcp man-in-the-middle proxy library, written in pure Python 3
Home-page: https://gitlab.com/seeklay/ku
Author: seeklay
Author-email: rudeboy@seeklay.icu
License: MIT
Download-URL: https://gitlab.com/seeklay/ku
Platform: OS Independent
Classifier: Programming Language :: Python :: 3.7
Classifier: Programming Language :: Python :: Implementation :: CPython
Classifier: Programming Language :: Python :: Implementation :: PyPy
Classifier: Operating System :: OS Independent
